{
  "data": {
    "article": {},
    "attachments": {},
    "author_id": "1778719380639014913",
    "conversation_id": "1901617927037800804",
    "created_at": "2025-03-17T12:53:38.000Z",
    "edit_controls": {
      "editable_until": "2025-03-17T13:53:38.000Z",
      "edits_remaining": 5,
      "is_edit_eligible": true
    },
    "edit_history_tweet_ids": [
      "1901617927037800804"
    ],
    "entities": {
      "urls": [
        {
          "display_url": "x.com/kunkouo/status…",
          "end": 36,
          "expanded_url": "https://twitter.com/kunkouo/status/1901521603264954636",
          "start": 13,
          "url": "https://t.co/ATS326MRGj"
        }
      ]
    },
    "geo": {},
    "id": "1901617927037800804",
    "lang": "zh",
    "note_tweet": {
      "entities": {}
    },
    "possibly_sensitive": false,
    "public_metrics": {
      "bookmark_count": 0,
      "impression_count": 0,
      "like_count": 0,
      "quote_count": 0,
      "reply_count": 0,
      "retweet_count": 0
    },
    "referenced_tweets": [
      {
        "id": "1901521603264954636",
        "type": "quoted"
      }
    ],
    "reply_settings": "everyone",
    "text": "我想做爱我想做爱我想做爱 https://t.co/ATS326MRGj"
  },
  "includes": {
    "tweets": [
      {
        "article": {},
        "attachments": {},
        "author_id": "1778719380639014913",
        "conversation_id": "1901617927037800804",
        "created_at": "2025-03-17T12:53:38.000Z",
        "edit_controls": {
          "editable_until": "2025-03-17T13:53:38.000Z",
          "edits_remaining": 5,
          "is_edit_eligible": true
        },
        "edit_history_tweet_ids": [
          "1901617927037800804"
        ],
        "entities": {
          "urls": [
            {
              "display_url": "x.com/kunkouo/status…",
              "end": 36,
              "expanded_url": "https://twitter.com/kunkouo/status/1901521603264954636",
              "start": 13,
              "url": "https://t.co/ATS326MRGj"
            }
          ]
        },
        "geo": {},
        "id": "1901617927037800804",
        "lang": "zh",
        "note_tweet": {
          "entities": {}
        },
        "possibly_sensitive": false,
        "public_metrics": {
          "bookmark_count": 0,
          "impression_count": 0,
          "like_count": 0,
          "quote_count": 0,
          "reply_count": 0,
          "retweet_count": 0
        },
        "referenced_tweets": [
          {
            "id": "1901521603264954636",
            "type": "quoted"
          }
        ],
        "reply_settings": "everyone",
        "text": "我想做爱我想做爱我想做爱 https://t.co/ATS326MRGj"
      },
      {
        "article": {},
        "attachments": {},
        "author_id": "1571103606300094467",
        "conversation_id": "1901521603264954636",
        "created_at": "2025-03-17T06:30:53.000Z",
        "edit_controls": {
          "editable_until": "2025-03-17T07:30:53.000Z",
          "edits_remaining": 5,
          "is_edit_eligible": true
        },
        "edit_history_tweet_ids": [
          "1901521603264954636"
        ],
        "entities": {},
        "geo": {},
        "id": "1901521603264954636",
        "lang": "zh",
        "note_tweet": {
          "entities": {}
        },
        "possibly_sensitive": false,
        "public_metrics": {
          "bookmark_count": 0,
          "impression_count": 9776,
          "like_count": 128,
          "quote_count": 2,
          "reply_count": 53,
          "retweet_count": 7
        },
        "reply_settings": "everyone",
        "text": "我想做爱\n我想做爱\n我想做爱\n我想做爱\n我想做爱\n我想做爱\n我想做爱\n我想做爱\n我想做爱\n我想做爱\n我想做爱\n我想做爱\n我想做爱\n我想做爱\n我想做爱\n我想做爱\n我想做爱\n我想做爱\n我想做爱\n我想做爱\n我想做爱\n我想做爱\n我想做爱\n我想做爱\n我想做爱\n我想做爱\n我想做爱\n我想做爱\n我想做爱\n我想做爱\n我想做爱"
      }
    ],
    "users": [
      {
        "created_at": "2024-04-12T09:38:51.000Z",
        "description": "双相 精分 酗酒 抽烟 嗑药/想交朋友/我的tg频道⬇️",
        "entities": {
          "url": {
            "urls": [
              {
                "display_url": "t.me/+tGPZagccCeE0M…",
                "end": 23,
                "expanded_url": "https://t.me/+tGPZagccCeE0M2I1",
                "start": 0,
                "url": "https://t.co/YOU43GttEH"
              }
            ]
          }
        },
        "id": "1778719380639014913",
        "name": "Sakura",
        "pinned_tweet_id": "1898429300963217469",
        "profile_image_url": "https://pbs.twimg.com/profile_images/1898374011295522816/t9_3UaIW_normal.jpg",
        "protected": false,
        "public_metrics": {
          "followers_count": 13,
          "following_count": 97,
          "like_count": 14,
          "listed_count": 0,
          "media_count": 15,
          "tweet_count": 79
        },
        "url": "https://t.co/YOU43GttEH",
        "username": "Ancde_1118",
        "verified": false
      },
      {
        "created_at": "2022-09-17T11:47:57.000Z",
        "description": "好事多磨｜碎碎念@psckk220",
        "entities": {
          "description": {
            "mentions": [
              {
                "end": 17,
                "start": 8,
                "username": "psckk220"
              }
            ]
          },
          "url": {
            "urls": [
              {
                "display_url": "wwwwwl.sogood9.com/#/register?cod…",
                "end": 23,
                "expanded_url": "https://wwwwwl.sogood9.com/#/register?code=Af7qU1Xd",
                "start": 0,
                "url": "https://t.co/pWZbyJLXOe"
              }
            ]
          }
        },
        "id": "1571103606300094467",
        "location": "自用vpn👉",
        "name": "猪柳蛋",
        "profile_image_url": "https://pbs.twimg.com/profile_images/1901185395993522176/Wb2Xkz4z_normal.jpg",
        "protected": false,
        "public_metrics": {
          "followers_count": 6655,
          "following_count": 177,
          "like_count": 11051,
          "listed_count": 13,
          "media_count": 47,
          "tweet_count": 8915
        },
        "url": "https://t.co/pWZbyJLXOe",
        "username": "Kunkouo",
        "verified": false
      }
    ]
  }
}