{
  "data": {
    "article": {},
    "attachments": {
      "media_keys": [
        "3_1992644191420334080"
      ]
    },
    "author_id": "1778719380639014913",
    "context_annotations": [
      {
        "domain": {
          "description": "Categories within Brand Verticals that narrow down the scope of Brands",
          "id": "46",
          "name": "Business Taxonomy"
        },
        "entity": {
          "description": "Brands, companies, advertisers and every non-person handle with the profit intent and related to foods & beverages such as snacks, soft drinks, beers.",
          "id": "1557696888568045569",
          "name": "Food & Beverage Business"
        }
      }
    ],
    "conversation_id": "1992644203076284658",
    "created_at": "2025-11-23T17:19:34.000Z",
    "edit_controls": {
      "editable_until": "2025-11-23T18:19:34.000Z",
      "edits_remaining": 5,
      "is_edit_eligible": true
    },
    "edit_history_tweet_ids": [
      "1992644203076284658"
    ],
    "entities": {
      "urls": [
        {
          "display_url": "pic.x.com/SFxPXf7eNE",
          "end": 23,
          "expanded_url": "https://x.com/Ancde_1118/status/1992644203076284658/photo/1",
          "media_key": "3_1992644191420334080",
          "start": 0,
          "url": "https://t.co/SFxPXf7eNE"
        }
      ]
    },
    "geo": {},
    "id": "1992644203076284658",
    "lang": "zxx",
    "note_tweet": {
      "entities": {}
    },
    "possibly_sensitive": false,
    "public_metrics": {
      "bookmark_count": 0,
      "impression_count": 0,
      "like_count": 0,
      "quote_count": 0,
      "reply_count": 0,
      "retweet_count": 0
    },
    "reply_settings": "everyone",
    "text": "https://t.co/SFxPXf7eNE"
  },
  "includes": {
    "media": [
      {
        "height": 2048,
        "media_key": "3_1992644191420334080",
        "public_metrics": {},
        "type": "photo",
        "url": "https://pbs.twimg.com/media/G6dLValawAAyyc0.jpg",
        "width": 1536
      }
    ],
    "tweets": [
      {
        "article": {},
        "attachments": {
          "media_keys": [
            "3_1992644191420334080"
          ]
        },
        "author_id": "1778719380639014913",
        "context_annotations": [
          {
            "domain": {
              "description": "Categories within Brand Verticals that narrow down the scope of Brands",
              "id": "46",
              "name": "Business Taxonomy"
            },
            "entity": {
              "description": "Brands, companies, advertisers and every non-person handle with the profit intent and related to foods & beverages such as snacks, soft drinks, beers.",
              "id": "1557696888568045569",
              "name": "Food & Beverage Business"
            }
          }
        ],
        "conversation_id": "1992644203076284658",
        "created_at": "2025-11-23T17:19:34.000Z",
        "edit_controls": {
          "editable_until": "2025-11-23T18:19:34.000Z",
          "edits_remaining": 5,
          "is_edit_eligible": true
        },
        "edit_history_tweet_ids": [
          "1992644203076284658"
        ],
        "entities": {
          "urls": [
            {
              "display_url": "pic.x.com/SFxPXf7eNE",
              "end": 23,
              "expanded_url": "https://x.com/Ancde_1118/status/1992644203076284658/photo/1",
              "media_key": "3_1992644191420334080",
              "start": 0,
              "url": "https://t.co/SFxPXf7eNE"
            }
          ]
        },
        "geo": {},
        "id": "1992644203076284658",
        "lang": "zxx",
        "note_tweet": {
          "entities": {}
        },
        "possibly_sensitive": false,
        "public_metrics": {
          "bookmark_count": 0,
          "impression_count": 0,
          "like_count": 0,
          "quote_count": 0,
          "reply_count": 0,
          "retweet_count": 0
        },
        "reply_settings": "everyone",
        "text": "https://t.co/SFxPXf7eNE"
      }
    ],
    "users": [
      {
        "created_at": "2024-04-12T09:38:51.000Z",
        "description": "双相 精分/我是穿孔师/tg@Sakura_sakura01118/我想交朋友 可以找我互fo",
        "id": "1778719380639014913",
        "name": "Sakura",
        "pinned_tweet_id": "1990862354285015102",
        "profile_image_url": "https://pbs.twimg.com/profile_images/1898374011295522816/t9_3UaIW_normal.jpg",
        "protected": false,
        "public_metrics": {
          "followers_count": 298,
          "following_count": 425,
          "like_count": 96,
          "listed_count": 1,
          "media_count": 119,
          "tweet_count": 730
        },
        "username": "Ancde_1118",
        "verified": false
      }
    ]
  }
}