{
  "data": {
    "article": {},
    "attachments": {},
    "author_id": "1778719380639014913",
    "conversation_id": "1904902147399102490",
    "created_at": "2025-03-26T14:23:57.000Z",
    "edit_controls": {
      "editable_until": "2025-03-26T15:23:57.000Z",
      "edits_remaining": 5,
      "is_edit_eligible": true
    },
    "edit_history_tweet_ids": [
      "1904902147399102490"
    ],
    "entities": {
      "urls": [
        {
          "display_url": "x.com/cnhpahky/statu…",
          "end": 33,
          "expanded_url": "https://twitter.com/cnhpahky/status/1904878867762077958",
          "start": 10,
          "url": "https://t.co/8pNyAXDYIG"
        }
      ]
    },
    "geo": {},
    "id": "1904902147399102490",
    "lang": "ja",
    "note_tweet": {
      "entities": {}
    },
    "possibly_sensitive": false,
    "public_metrics": {
      "bookmark_count": 0,
      "impression_count": 7,
      "like_count": 0,
      "quote_count": 0,
      "reply_count": 0,
      "retweet_count": 0
    },
    "referenced_tweets": [
      {
        "id": "1904878867762077958",
        "type": "quoted"
      }
    ],
    "reply_settings": "everyone",
    "text": "我也想抱抱和交朋友 https://t.co/8pNyAXDYIG"
  },
  "includes": {
    "media": [
      {
        "height": 800,
        "media_key": "3_1904878860300410915",
        "public_metrics": {},
        "type": "photo",
        "url": "https://pbs.twimg.com/media/Gm99OyBbYCMqraK.jpg",
        "width": 800
      }
    ],
    "tweets": [
      {
        "article": {},
        "attachments": {},
        "author_id": "1778719380639014913",
        "conversation_id": "1904902147399102490",
        "created_at": "2025-03-26T14:23:57.000Z",
        "edit_controls": {
          "editable_until": "2025-03-26T15:23:57.000Z",
          "edits_remaining": 5,
          "is_edit_eligible": true
        },
        "edit_history_tweet_ids": [
          "1904902147399102490"
        ],
        "entities": {
          "urls": [
            {
              "display_url": "x.com/cnhpahky/statu…",
              "end": 33,
              "expanded_url": "https://twitter.com/cnhpahky/status/1904878867762077958",
              "start": 10,
              "url": "https://t.co/8pNyAXDYIG"
            }
          ]
        },
        "geo": {},
        "id": "1904902147399102490",
        "lang": "ja",
        "note_tweet": {
          "entities": {}
        },
        "possibly_sensitive": false,
        "public_metrics": {
          "bookmark_count": 0,
          "impression_count": 7,
          "like_count": 0,
          "quote_count": 0,
          "reply_count": 0,
          "retweet_count": 0
        },
        "referenced_tweets": [
          {
            "id": "1904878867762077958",
            "type": "quoted"
          }
        ],
        "reply_settings": "everyone",
        "text": "我也想抱抱和交朋友 https://t.co/8pNyAXDYIG"
      },
      {
        "article": {},
        "attachments": {
          "media_keys": [
            "3_1904878860300410915"
          ]
        },
        "author_id": "1788485889225834496",
        "conversation_id": "1904878867762077958",
        "created_at": "2025-03-26T12:51:27.000Z",
        "edit_controls": {
          "editable_until": "2025-03-26T13:51:27.000Z",
          "edits_remaining": 5,
          "is_edit_eligible": true
        },
        "edit_history_tweet_ids": [
          "1904878867762077958"
        ],
        "entities": {
          "urls": [
            {
              "display_url": "pic.x.com/hKE8U7hqlN",
              "end": 54,
              "expanded_url": "https://x.com/CnHpaHky/status/1904878867762077958/photo/1",
              "media_key": "3_1904878860300410915",
              "start": 31,
              "url": "https://t.co/hKE8U7hqlN"
            }
          ]
        },
        "geo": {},
        "id": "1904878867762077958",
        "lang": "zh",
        "note_tweet": {
          "entities": {}
        },
        "possibly_sensitive": false,
        "public_metrics": {
          "bookmark_count": 0,
          "impression_count": 352,
          "like_count": 21,
          "quote_count": 2,
          "reply_count": 2,
          "retweet_count": 10
        },
        "reply_settings": "everyone",
        "text": "晚上好喵。\n想和我交朋友或者要抱抱可以转发这个帖子🥰❤️❤️ https://t.co/hKE8U7hqlN"
      }
    ],
    "users": [
      {
        "created_at": "2024-04-12T09:38:51.000Z",
        "description": "双相 精分 酗酒 抽烟 嗑药/想交朋友/我的tg频道⬇️",
        "entities": {
          "url": {
            "urls": [
              {
                "display_url": "t.me/+tGPZagccCeE0M…",
                "end": 23,
                "expanded_url": "https://t.me/+tGPZagccCeE0M2I1",
                "start": 0,
                "url": "https://t.co/YOU43GttEH"
              }
            ]
          }
        },
        "id": "1778719380639014913",
        "name": "Sakura",
        "pinned_tweet_id": "1898429300963217469",
        "profile_image_url": "https://pbs.twimg.com/profile_images/1898374011295522816/t9_3UaIW_normal.jpg",
        "protected": false,
        "public_metrics": {
          "followers_count": 28,
          "following_count": 113,
          "like_count": 17,
          "listed_count": 0,
          "media_count": 24,
          "tweet_count": 185
        },
        "url": "https://t.co/YOU43GttEH",
        "username": "Ancde_1118",
        "verified": false
      },
      {
        "created_at": "2024-05-09T08:27:31.000Z",
        "description": "我叫阳阳，ASD在学着如何成为人类，欢迎私信。⭐️ @SubaAyana @Littlecat111007 @cinianxiaogou @quitee123 @ming_li19274",
        "entities": {
          "description": {
            "mentions": [
              {
                "end": 36,
                "start": 26,
                "username": "SubaAyana"
              },
              {
                "end": 53,
                "start": 37,
                "username": "Littlecat111007"
              },
              {
                "end": 68,
                "start": 54,
                "username": "cinianxiaogou"
              },
              {
                "end": 79,
                "start": 69,
                "username": "quitee123"
              },
              {
                "end": 93,
                "start": 80,
                "username": "ming_li19274"
              }
            ]
          }
        },
        "id": "1788485889225834496",
        "location": "北京安定医院",
        "name": "fallen stars",
        "pinned_tweet_id": "1904764251086189049",
        "profile_image_url": "https://pbs.twimg.com/profile_images/1898402237363507200/Wx3H_9yY_normal.jpg",
        "protected": false,
        "public_metrics": {
          "followers_count": 2374,
          "following_count": 1571,
          "like_count": 10392,
          "listed_count": 4,
          "media_count": 135,
          "tweet_count": 4614
        },
        "username": "CnHpaHky",
        "verified": false
      }
    ]
  }
}